flask_execute/__init__.py
flask_execute/cli.py
flask_execute/ext.py
flask_execute/futures.py
flask_execute/managers.py
flask_execute/plugin.py
tests/isolated/__init__.py
tests/isolated/test_direct.py
tests/isolated/test_factory.py
tests/resources/__init__.py
tests/resources/direct.py
tests/resources/factory.py
Flask_Execute-0.1.6.dist-info/LICENSE
Flask_Execute-0.1.6.dist-info/METADATA
Flask_Execute-0.1.6.dist-info/WHEEL
Flask_Execute-0.1.6.dist-info/top_level.txt
Flask_Execute-0.1.6.dist-info/RECORD
