Metadata-Version: 2.1
Name: Flask-Execute
Version: 0.1.6
Summary: Simple Celery integration for Flask applications.
Home-page: https://github.com/bprinty/Flask-Execute
Author: Blake Printy
Author-email: bprinty@gmail.com
License: MIT
Keywords: flask-execute,flask,celery,executor,execute,dispatch,dask,distributed,futures,concurrent.futures,remote,executor,flask-celery,task,queue
Platform: any
Classifier: Environment :: Web Environment
Classifier: Intended Audience :: Developers
Classifier: License :: OSI Approved :: MIT License
Classifier: Operating System :: OS Independent
Classifier: Programming Language :: Python
Classifier: Topic :: Internet :: WWW/HTTP :: Dynamic Content
Classifier: Topic :: Software Development :: Libraries :: Python Modules
Classifier: Natural Language :: English
Classifier: Programming Language :: Python :: 2
Classifier: Programming Language :: Python :: 2.6
Classifier: Programming Language :: Python :: 2.7
Classifier: Programming Language :: Python :: 3
Classifier: Programming Language :: Python :: 3.3
Classifier: Programming Language :: Python :: 3.4
Classifier: Programming Language :: Python :: 3.5
Classifier: Programming Language :: Python :: 3.6
Classifier: Programming Language :: Python :: 3.7
Requires-Dist: Flask
Requires-Dist: celery
Requires-Dist: flower
Requires-Dist: redis
